README.md
setup.py
wsit/__init__.py
wsit/main/__init__.py
wsit/main/com/__init__.py
wsit/main/com/vsi/__init__.py
wsit/main/com/vsi/wsi/__init__.py
wsit/main/com/vsi/wsi/big_decimal.py
wsit/main/com/vsi/wsi/i_wsi_native_shell.py
wsit/main/com/vsi/wsi/i_xa_resource.py
wsit/main/com/vsi/wsi/i_xid.py
wsit/main/com/vsi/wsi/invalid_state_exception.py
wsit/main/com/vsi/wsi/no_server_exception.py
wsit/main/com/vsi/wsi/server_config.py
wsit/main/com/vsi/wsi/string_qualify.py
wsit/main/com/vsi/wsi/wsi_acms_context.py
wsit/main/com/vsi/wsi/wsi_acms_context_editor.py
wsit/main/com/vsi/wsi/wsi_array.py
wsit/main/com/vsi/wsi/wsi_buffer.py
wsit/main/com/vsi/wsi/wsi_connect_exception.py
wsit/main/com/vsi/wsi/wsi_decimal.py
wsit/main/com/vsi/wsi/wsi_exception.py
wsit/main/com/vsi/wsi/wsi_ipc_context.py
wsit/main/com/vsi/wsi/wsi_msg_packager.py
wsit/main/com/vsi/wsi/wsi_rtl_version.py
wsit/main/com/vsi/wsi/wsi_server_exception.py
wsit/main/com/vsi/wsi/wsi_structure.py
wsit/main/com/vsi/wsi/wsi_utils.py
wsit/main/com/vsi/wsi/wsi_v2_structure.py
wsit/main/com/vsi/wsi/wsi_xa_desc.py
wsit/main/com/vsi/wsi/wsi_xid_cache.py
wsit/main/com/vsi/wsi/wsi_xid_impl.py
wsit/main/com/vsi/wsi/wsi_xid_map.py
wsit/main/com/vsi/wsi/xa_exception.py
wsit/main/javax/__init__.py
wsit/main/javax/xml/__init__.py
wsit/main/javax/xml/rpc/__init__.py
wsit/main/javax/xml/rpc/holders/__init__.py
wsit/test/__init__.py
wsit/test/com/__init__.py
wsit/test/com/vsi/__init__.py
wsit/test/com/vsi/wsi/__init__.py
wsit/test/com/vsi/wsi/big_decimal_test.py
wsit/test/com/vsi/wsi/invalid_state_exception_test.py
wsit/test/com/vsi/wsi/main.py
wsit/test/com/vsi/wsi/main2.py
wsit/test/com/vsi/wsi/no_server_exception_test.py
wsit/test/com/vsi/wsi/server_config_test.py
wsit/test/com/vsi/wsi/string_qualify_test.py
wsit/test/com/vsi/wsi/wsi_acms_context_editor_test.py
wsit/test/com/vsi/wsi/wsi_acms_context_test.py
wsit/test/com/vsi/wsi/wsi_array_test.py
wsit/test/com/vsi/wsi/wsi_buffer_test.py
wsit_python.egg-info/PKG-INFO
wsit_python.egg-info/SOURCES.txt
wsit_python.egg-info/dependency_links.txt
wsit_python.egg-info/not-zip-safe
wsit_python.egg-info/requires.txt
wsit_python.egg-info/top_level.txt