Metadata-Version: 2.1
Name: wsit-python
Version: 1.0
Summary: Web Services Integration Toolkit
Home-page: https://vmssoftware.com/products/web-services-integration-toolkit/
Author: VMS Software, Inc.
License: MIT
Platform: UNKNOWN
